{"MoveLists":[{"Moves":[{"Name":"STAND_ACT_SHOT","Index":0,"FirstHitboxFrame":0,"LastHitboxFrame":40,"InterruptFrame":-1,"TotalTicks":40,"ReturnToOriginalPosition":7,"Slide":0.0,"unk3":0.0,"unk4":0.0,"unk5":0.0,"unk6":0.0,"unk7":0.0,"Flag":0,"unk9":0,"numberOfTypes":2,"unk13":0,"HeaderSize":64,"Unknown12":0,"Unknown13":0,"Unknown14":0,"Unknown15":0,"Unknown16":0,"Unknown17":0,"Unknown18":0.0,"Unknown19":0,"Unknown20":0,"Unknown21":0,"Unknown22":0,"AutoCancels":null,"Type1s":null,"Forces":[{"TickStart":0,"TickEnd":1,"Amount":0.06,"Flag":"HorizontalSpeed"},{"TickStart":0,"TickEnd":1,"Amount":0.08,"Flag":"VerticalSpeed"},{"TickStart":0,"TickEnd":1,"Amount":-0.008,"Flag":"VerticalAcceleration"}],"Cancels":null,"Others":null,"Hitboxes":[{"TickStart":0,"TickEnd":40,"X":0.0,"Y":0.0,"Z":0.0,"Width":0.2,"Height":0.2,"Unknown1":0,"Unknown2":25,"Unknown3":25,"Unknown4":25,"Unknown5":0,"Unknown6":72,"Unknown7":0,"Unknown8":2560,"NumberOfHits":1,"HitType":0,"JuggleLimit":0,"JuggleIncrease":1,"Flag4":0,"HitboxEffectIndex":0,"Unknown10":0,"Unknown11":0}],"Hurtboxes":null,"PhysicsBoxes":null,"Positions":null},null,{"Name":"VS_01_BANANA","Index":2,"FirstHitboxFrame":0,"LastHitboxFrame":200,"InterruptFrame":-1,"TotalTicks":200,"ReturnToOriginalPosition":7,"Slide":0.0,"unk3":0.0,"unk4":0.0,"unk5":0.0,"unk6":0.0,"unk7":0.0,"Flag":0,"unk9":0,"numberOfTypes":3,"unk13":64,"HeaderSize":88,"Unknown12":1005,"Unknown13":-1,"Unknown14":-1,"Unknown15":-1,"Unknown16":-1,"Unknown17":-1,"Unknown18":1.0,"Unknown19":-1,"Unknown20":0,"Unknown21":0,"Unknown22":0,"AutoCancels":null,"Type1s":null,"Forces":null,"Cancels":null,"Others":null,"Hitboxes":[{"TickStart":0,"TickEnd":200,"X":-0.2,"Y":0.0,"Z":0.0,"Width":0.4,"Height":0.3,"Unknown1":0,"Unknown2":25,"Unknown3":25,"Unknown4":25,"Unknown5":0,"Unknown6":76,"Unknown7":0,"Unknown8":17920,"NumberOfHits":1,"HitType":0,"JuggleLimit":1,"JuggleIncrease":1,"Flag4":0,"HitboxEffectIndex":2,"Unknown10":0,"Unknown11":0}],"Hurtboxes":null,"PhysicsBoxes":null,"Positions":null},null,{"Name":"VS_01_DRINK","Index":4,"FirstHitboxFrame":0,"LastHitboxFrame":80,"InterruptFrame":-1,"TotalTicks":80,"ReturnToOriginalPosition":23,"Slide":0.0,"unk3":0.0,"unk4":0.0,"unk5":0.0,"unk6":0.0,"unk7":0.0,"Flag":0,"unk9":1,"numberOfTypes":4,"unk13":64,"HeaderSize":88,"Unknown12":1000,"Unknown13":-1,"Unknown14":-1,"Unknown15":-1,"Unknown16":-1,"Unknown17":-1,"Unknown18":1.0,"Unknown19":-1,"Unknown20":0,"Unknown21":0,"Unknown22":0,"AutoCancels":null,"Type1s":null,"Forces":[{"TickStart":0,"TickEnd":1,"Amount":0.03,"Flag":"HorizontalSpeed"}],"Cancels":null,"Others":null,"Hitboxes":[{"TickStart":0,"TickEnd":80,"X":0.0,"Y":0.0,"Z":0.0,"Width":0.4,"Height":0.3,"Unknown1":0,"Unknown2":25,"Unknown3":25,"Unknown4":25,"Unknown5":0,"Unknown6":76,"Unknown7":0,"Unknown8":17920,"NumberOfHits":1,"HitType":0,"JuggleLimit":0,"JuggleIncrease":1,"Flag4":0,"HitboxEffectIndex":4,"Unknown10":0,"Unknown11":0}],"Hurtboxes":null,"PhysicsBoxes":null,"Positions":null}],"Unknown1":-1}],"HitboxEffectses":[{"Index":0,"HIT_STAND":{"Type":1,"Index":0,"DamageType":0,"Unused1":0,"NumberOfType1":1,"NumberOfType2":1,"Unused2":0,"Damage":10,"Stun":0,"Index9":0,"EXBuildAttacker":0,"EXBuildDefender":0,"Index12":0,"HitStunFramesAttacker":1,"HitStunFramesDefender":1,"FuzzyEffect":0,"RecoveryAnimationFramesDefender":0,"Index17":0,"Index18":1,"Index19":0,"KnockBack":0.0,"FallSpeed":0.5,"Index22":0,"Index23":0,"Index24":0,"Index25":0,"OffsetToStartOfType1":76,"OffsetToStartOfType2":88,"Type1s":[{"Unknown1":0,"SoundType":50,"Unknown3":0,"Unknown4":0}],"Type2s":[{"EffectType1":0,"EffectType2":0,"EffectType3":1,"Unknown4":0,"EffectPosition":-1,"Unknown6":0,"Unknown7":0,"Unknown8":0,"Unknown9":0,"Size":1.0,"Unknown11":0}]},"HIT_CROUCH":{"Type":1,"Index":0,"DamageType":0,"Unused1":0,"NumberOfType1":1,"NumberOfType2":1,"Unused2":0,"Damage":10,"Stun":0,"Index9":0,"EXBuildAttacker":0,"EXBuildDefender":0,"Index12":0,"HitStunFramesAttacker":1,"HitStunFramesDefender":1,"FuzzyEffect":0,"RecoveryAnimationFramesDefender":0,"Index17":0,"Index18":1,"Index19":0,"KnockBack":0.0,"FallSpeed":0.5,"Index22":0,"Index23":0,"Index24":0,"Index25":0,"OffsetToStartOfType1":76,"OffsetToStartOfType2":88,"Type1s":[{"Unknown1":0,"SoundType":50,"Unknown3":0,"Unknown4":0}],"Type2s":[{"EffectType1":0,"EffectType2":0,"EffectType3":1,"Unknown4":0,"EffectPosition":-1,"Unknown6":0,"Unknown7":0,"Unknown8":0,"Unknown9":0,"Size":1.0,"Unknown11":0}]},"HIT_AIR":{"Type":1,"Index":0,"DamageType":0,"Unused1":0,"NumberOfType1":1,"NumberOfType2":1,"Unused2":0,"Damage":10,"Stun":0,"Index9":0,"EXBuildAttacker":0,"EXBuildDefender":0,"Index12":0,"HitStunFramesAttacker":1,"HitStunFramesDefender":1,"FuzzyEffect":0,"RecoveryAnimationFramesDefender":20,"Index17":0,"Index18":1,"Index19":0,"KnockBack":0.3,"FallSpeed":0.5,"Index22":0,"Index23":0,"Index24":0,"Index25":0,"OffsetToStartOfType1":76,"OffsetToStartOfType2":88,"Type1s":[{"Unknown1":0,"SoundType":50,"Unknown3":0,"Unknown4":0}],"Type2s":[{"EffectType1":0,"EffectType2":0,"EffectType3":1,"Unknown4":0,"EffectPosition":-1,"Unknown6":0,"Unknown7":0,"Unknown8":0,"Unknown9":0,"Size":1.0,"Unknown11":0}]},"HIT_UNKNOWN":{"Type":1,"Index":0,"DamageType":0,"Unused1":0,"NumberOfType1":1,"NumberOfType2":1,"Unused2":0,"Damage":10,"Stun":0,"Index9":0,"EXBuildAttacker":0,"EXBuildDefender":0,"Index12":0,"HitStunFramesAttacker":1,"HitStunFramesDefender":1,"FuzzyEffect":0,"RecoveryAnimationFramesDefender":0,"Index17":0,"Index18":1,"Index19":0,"KnockBack":0.0,"FallSpeed":0.5,"Index22":0,"Index23":0,"Index24":0,"Index25":0,"OffsetToStartOfType1":76,"OffsetToStartOfType2":88,"Type1s":[{"Unknown1":0,"SoundType":50,"Unknown3":0,"Unknown4":0}],"Type2s":[{"EffectType1":0,"EffectType2":0,"EffectType3":1,"Unknown4":0,"EffectPosition":-1,"Unknown6":0,"Unknown7":0,"Unknown8":0,"Unknown9":0,"Size":1.0,"Unknown11":0}]},"HIT_UNKNOWN2":{"Type":0,"Index":-1,"DamageType":1,"Unused1":0,"NumberOfType1":1,"NumberOfType2":1,"Unused2":0,"Damage":0,"Stun":0,"Index9":0,"EXBuildAttacker":0,"EXBuildDefender":0,"Index12":0,"HitStunFramesAttacker":0,"HitStunFramesDefender":0,"FuzzyEffect":0,"RecoveryAnimationFramesDefender":0,"Index17":0,"Index18":257,"Index19":0,"KnockBack":0.0,"FallSpeed":0.0,"Index22":0,"Index23":0,"Index24":0,"Index25":0,"OffsetToStartOfType1":76,"OffsetToStartOfType2":88,"Type1s":[{"Unknown1":0,"SoundType":50,"Unknown3":0,"Unknown4":0}],"Type2s":[{"EffectType1":0,"EffectType2":0,"EffectType3":1,"Unknown4":0,"EffectPosition":-1,"Unknown6":0,"Unknown7":0,"Unknown8":0,"Unknown9":0,"Size":1.0,"Unknown11":0}]},"GUARD_STAND":{"Type":2,"Index":0,"DamageType":0,"Unused1":0,"NumberOfType1":1,"NumberOfType2":1,"Unused2":0,"Damage":0,"Stun":0,"Index9":0,"EXBuildAttacker":0,"EXBuildDefender":0,"Index12":0,"HitStunFramesAttacker":1,"HitStunFramesDefender":1,"FuzzyEffect":0,"RecoveryAnimationFramesDefender":14,"Index17":0,"Index18":1,"Index19":0,"KnockBack":0.0,"FallSpeed":0.5,"Index22":0,"Index23":0,"Index24":0,"Index25":0,"OffsetToStartOfType1":76,"OffsetToStartOfType2":88,"Type1s":[{"Unknown1":0,"SoundType":300,"Unknown3":0,"Unknown4":0}],"Type2s":[{"EffectType1":0,"EffectType2":0,"EffectType3":20,"Unknown4":0,"EffectPosition":-1,"Unknown6":0,"Unknown7":0,"Unknown8":0,"Unknown9":0,"Size":1.0,"Unknown11":0}]},"GUARD_CROUCH":{"Type":2,"Index":0,"DamageType":0,"Unused1":0,"NumberOfType1":1,"NumberOfType2":1,"Unused2":0,"Damage":0,"Stun":0,"Index9":0,"EXBuildAttacker":0,"EXBuildDefender":0,"Index12":0,"HitStunFramesAttacker":1,"HitStunFramesDefender":1,"FuzzyEffect":0,"RecoveryAnimationFramesDefender":14,"Index17":0,"Index18":1,"Index19":0,"KnockBack":0.0,"FallSpeed":0.5,"Index22":0,"Index23":0,"Index24":0,"Index25":0,"OffsetToStartOfType1":76,"OffsetToStartOfType2":88,"Type1s":[{"Unknown1":0,"SoundType":300,"Unknown3":0,"Unknown4":0}],"Type2s":[{"EffectType1":0,"EffectType2":0,"EffectType3":20,"Unknown4":0,"EffectPosition":-1,"Unknown6":0,"Unknown7":0,"Unknown8":0,"Unknown9":0,"Size":1.0,"Unknown11":0}]},"GUARD_AIR":{"Type":2,"Index":0,"DamageType":0,"Unused1":0,"NumberOfType1":1,"NumberOfType2":1,"Unused2":0,"Damage":0,"Stun":0,"Index9":0,"EXBuildAttacker":0,"EXBuildDefender":0,"Index12":0,"HitStunFramesAttacker":1,"HitStunFramesDefender":1,"FuzzyEffect":0,"RecoveryAnimationFramesDefender":14,"Index17":0,"Index18":1,"Index19":0,"KnockBack":0.0,"FallSpeed":0.5,"Index22":0,"Index23":0,"Index24":0,"Index25":0,"OffsetToStartOfType1":76,"OffsetToStartOfType2":88,"Type1s":[{"Unknown1":0,"SoundType":300,"Unknown3":0,"Unknown4":0}],"Type2s":[{"EffectType1":0,"EffectType2":0,"EffectType3":20,"Unknown4":0,"EffectPosition":-1,"Unknown6":0,"Unknown7":0,"Unknown8":0,"Unknown9":0,"Size":1.0,"Unknown11":0}]},"GUARD_UNKNOWN":{"Type":2,"Index":0,"DamageType":0,"Unused1":0,"NumberOfType1":1,"NumberOfType2":1,"Unused2":0,"Damage":0,"Stun":0,"Index9":0,"EXBuildAttacker":0,"EXBuildDefender":0,"Index12":0,"HitStunFramesAttacker":1,"HitStunFramesDefender":1,"FuzzyEffect":0,"RecoveryAnimationFramesDefender":14,"Index17":0,"Index18":1,"Index19":0,"KnockBack":0.0,"FallSpeed":0.5,"Index22":0,"Index23":0,"Index24":0,"Index25":0,"OffsetToStartOfType1":76,"OffsetToStartOfType2":88,"Type1s":[{"Unknown1":0,"SoundType":300,"Unknown3":0,"Unknown4":0}],"Type2s":[{"EffectType1":0,"EffectType2":0,"EffectType3":20,"Unknown4":0,"EffectPosition":-1,"Unknown6":0,"Unknown7":0,"Unknown8":0,"Unknown9":0,"Size":1.0,"Unknown11":0}]},"GUARD_UNKNOWN2":{"Type":0,"Index":-1,"DamageType":1,"Unused1":0,"NumberOfType1":1,"NumberOfType2":1,"Unused2":0,"Damage":0,"Stun":0,"Index9":0,"EXBuildAttacker":0,"EXBuildDefender":0,"Index12":0,"HitStunFramesAttacker":0,"HitStunFramesDefender":0,"FuzzyEffect":0,"RecoveryAnimationFramesDefender":0,"Index17":0,"Index18":257,"Index19":0,"KnockBack":0.0,"FallSpeed":0.0,"Index22":0,"Index23":0,"Index24":0,"Index25":0,"OffsetToStartOfType1":76,"OffsetToStartOfType2":88,"Type1s":[{"Unknown1":0,"SoundType":300,"Unknown3":0,"Unknown4":0}],"Type2s":[{"EffectType1":0,"EffectType2":0,"EffectType3":20,"Unknown4":0,"EffectPosition":-1,"Unknown6":0,"Unknown7":0,"Unknown8":0,"Unknown9":0,"Size":1.0,"Unknown11":0}]},"COUNTERHIT_STAND":{"Type":1,"Index":0,"DamageType":0,"Unused1":0,"NumberOfType1":1,"NumberOfType2":1,"Unused2":0,"Damage":12,"Stun":0,"Index9":0,"EXBuildAttacker":0,"EXBuildDefender":0,"Index12":0,"HitStunFramesAttacker":1,"HitStunFramesDefender":1,"FuzzyEffect":0,"RecoveryAnimationFramesDefender":0,"Index17":0,"Index18":1,"Index19":0,"KnockBack":0.0,"FallSpeed":0.5,"Index22":0,"Index23":0,"Index24":0,"Index25":0,"OffsetToStartOfType1":76,"OffsetToStartOfType2":88,"Type1s":[{"Unknown1":0,"SoundType":50,"Unknown3":0,"Unknown4":0}],"Type2s":[{"EffectType1":0,"EffectType2":0,"EffectType3":1,"Unknown4":0,"EffectPosition":-1,"Unknown6":0,"Unknown7":0,"Unknown8":0,"Unknown9":0,"Size":1.0,"Unknown11":0}]},"COUNTERHIT_CROUCH":{"Type":1,"Index":0,"DamageType":0,"Unused1":0,"NumberOfType1":1,"NumberOfType2":1,"Unused2":0,"Damage":12,"Stun":0,"Index9":0,"EXBuildAttacker":0,"EXBuildDefender":0,"Index12":0,"HitStunFramesAttacker":1,"HitStunFramesDefender":1,"FuzzyEffect":0,"RecoveryAnimationFramesDefender":0,"Index17":0,"Index18":1,"Index19":0,"KnockBack":0.0,"FallSpeed":0.5,"Index22":0,"Index23":0,"Index24":0,"Index25":0,"OffsetToStartOfType1":76,"OffsetToStartOfType2":88,"Type1s":[{"Unknown1":0,"SoundType":50,"Unknown3":0,"Unknown4":0}],"Type2s":[{"EffectType1":0,"EffectType2":0,"EffectType3":1,"Unknown4":0,"EffectPosition":-1,"Unknown6":0,"Unknown7":0,"Unknown8":0,"Unknown9":0,"Size":1.0,"Unknown11":0}]},"COUNTERHIT_AIR":{"Type":1,"Index":0,"DamageType":0,"Unused1":0,"NumberOfType1":1,"NumberOfType2":1,"Unused2":0,"Damage":12,"Stun":0,"Index9":0,"EXBuildAttacker":0,"EXBuildDefender":0,"Index12":0,"HitStunFramesAttacker":1,"HitStunFramesDefender":1,"FuzzyEffect":0,"RecoveryAnimationFramesDefender":20,"Index17":0,"Index18":1,"Index19":0,"KnockBack":0.3,"FallSpeed":0.5,"Index22":0,"Index23":0,"Index24":0,"Index25":0,"OffsetToStartOfType1":76,"OffsetToStartOfType2":88,"Type1s":[{"Unknown1":0,"SoundType":50,"Unknown3":0,"Unknown4":0}],"Type2s":[{"EffectType1":0,"EffectType2":0,"EffectType3":1,"Unknown4":0,"EffectPosition":-1,"Unknown6":0,"Unknown7":0,"Unknown8":0,"Unknown9":0,"Size":1.0,"Unknown11":0}]},"COUNTERHIT_UNKNOWN":{"Type":1,"Index":0,"DamageType":0,"Unused1":0,"NumberOfType1":1,"NumberOfType2":1,"Unused2":0,"Damage":12,"Stun":0,"Index9":0,"EXBuildAttacker":0,"EXBuildDefender":0,"Index12":0,"HitStunFramesAttacker":1,"HitStunFramesDefender":1,"FuzzyEffect":0,"RecoveryAnimationFramesDefender":0,"Index17":0,"Index18":1,"Index19":0,"KnockBack":0.0,"FallSpeed":0.5,"Index22":0,"Index23":0,"Index24":0,"Index25":0,"OffsetToStartOfType1":76,"OffsetToStartOfType2":88,"Type1s":[{"Unknown1":0,"SoundType":50,"Unknown3":0,"Unknown4":0}],"Type2s":[{"EffectType1":0,"EffectType2":0,"EffectType3":1,"Unknown4":0,"EffectPosition":-1,"Unknown6":0,"Unknown7":0,"Unknown8":0,"Unknown9":0,"Size":1.0,"Unknown11":0}]},"COUNTERHIT_UNKNOWN2":{"Type":0,"Index":-1,"DamageType":1,"Unused1":0,"NumberOfType1":1,"NumberOfType2":1,"Unused2":0,"Damage":0,"Stun":0,"Index9":0,"EXBuildAttacker":0,"EXBuildDefender":0,"Index12":0,"HitStunFramesAttacker":0,"HitStunFramesDefender":0,"FuzzyEffect":0,"RecoveryAnimationFramesDefender":0,"Index17":0,"Index18":257,"Index19":0,"KnockBack":0.0,"FallSpeed":0.0,"Index22":0,"Index23":0,"Index24":0,"Index25":0,"OffsetToStartOfType1":76,"OffsetToStartOfType2":88,"Type1s":[{"Unknown1":0,"SoundType":50,"Unknown3":0,"Unknown4":0}],"Type2s":[{"EffectType1":0,"EffectType2":0,"EffectType3":1,"Unknown4":0,"EffectPosition":-1,"Unknown6":0,"Unknown7":0,"Unknown8":0,"Unknown9":0,"Size":1.0,"Unknown11":0}]},"UNKNOWN_STAND":{"Type":0,"Index":-1,"DamageType":1,"Unused1":0,"NumberOfType1":0,"NumberOfType2":0,"Unused2":0,"Damage":10,"Stun":0,"Index9":0,"EXBuildAttacker":0,"EXBuildDefender":0,"Index12":0,"HitStunFramesAttacker":0,"HitStunFramesDefender":0,"FuzzyEffect":0,"RecoveryAnimationFramesDefender":0,"Index17":0,"Index18":257,"Index19":0,"KnockBack":0.0,"FallSpeed":0.0,"Index22":0,"Index23":0,"Index24":0,"Index25":0,"OffsetToStartOfType1":0,"OffsetToStartOfType2":0,"Type1s":[],"Type2s":[]},"UNKNOWN_CROUCH":{"Type":0,"Index":-1,"DamageType":1,"Unused1":0,"NumberOfType1":0,"NumberOfType2":0,"Unused2":0,"Damage":10,"Stun":0,"Index9":0,"EXBuildAttacker":0,"EXBuildDefender":0,"Index12":0,"HitStunFramesAttacker":0,"HitStunFramesDefender":0,"FuzzyEffect":0,"RecoveryAnimationFramesDefender":0,"Index17":0,"Index18":257,"Index19":0,"KnockBack":0.0,"FallSpeed":0.0,"Index22":0,"Index23":0,"Index24":0,"Index25":0,"OffsetToStartOfType1":0,"OffsetToStartOfType2":0,"Type1s":[],"Type2s":[]},"UNKNOWN_AIR":{"Type":0,"Index":-1,"DamageType":1,"Unused1":0,"NumberOfType1":0,"NumberOfType2":0,"Unused2":0,"Damage":10,"Stun":0,"Index9":0,"EXBuildAttacker":0,"EXBuildDefender":0,"Index12":0,"HitStunFramesAttacker":0,"HitStunFramesDefender":0,"FuzzyEffect":0,"RecoveryAnimationFramesDefender":0,"Index17":0,"Index18":257,"Index19":0,"KnockBack":0.0,"FallSpeed":0.0,"Index22":0,"Index23":0,"Index24":0,"Index25":0,"OffsetToStartOfType1":0,"OffsetToStartOfType2":0,"Type1s":[],"Type2s":[]},"UNKNOWN_UNKNOWN":{"Type":0,"Index":-1,"DamageType":1,"Unused1":0,"NumberOfType1":0,"NumberOfType2":0,"Unused2":0,"Damage":10,"Stun":0,"Index9":0,"EXBuildAttacker":0,"EXBuildDefender":0,"Index12":0,"HitStunFramesAttacker":0,"HitStunFramesDefender":0,"FuzzyEffect":0,"RecoveryAnimationFramesDefender":0,"Index17":0,"Index18":257,"Index19":0,"KnockBack":0.0,"FallSpeed":0.0,"Index22":0,"Index23":0,"Index24":0,"Index25":0,"OffsetToStartOfType1":0,"OffsetToStartOfType2":0,"Type1s":[],"Type2s":[]},"UNKNOWN_UNKNOWN2":{"Type":0,"Index":-1,"DamageType":1,"Unused1":0,"NumberOfType1":0,"NumberOfType2":0,"Unused2":0,"Damage":0,"Stun":0,"Index9":0,"EXBuildAttacker":0,"EXBuildDefender":0,"Index12":0,"HitStunFramesAttacker":0,"HitStunFramesDefender":0,"FuzzyEffect":0,"RecoveryAnimationFramesDefender":0,"Index17":0,"Index18":257,"Index19":0,"KnockBack":0.0,"FallSpeed":0.0,"Index22":0,"Index23":0,"Index24":0,"Index25":0,"OffsetToStartOfType1":0,"OffsetToStartOfType2":0,"Type1s":[],"Type2s":[]}},{"Index":1,"HIT_STAND":null,"HIT_CROUCH":null,"HIT_AIR":null,"HIT_UNKNOWN":null,"HIT_UNKNOWN2":null,"GUARD_STAND":null,"GUARD_CROUCH":null,"GUARD_AIR":null,"GUARD_UNKNOWN":null,"GUARD_UNKNOWN2":null,"COUNTERHIT_STAND":null,"COUNTERHIT_CROUCH":null,"COUNTERHIT_AIR":null,"COUNTERHIT_UNKNOWN":null,"COUNTERHIT_UNKNOWN2":null,"UNKNOWN_STAND":null,"UNKNOWN_CROUCH":null,"UNKNOWN_AIR":null,"UNKNOWN_UNKNOWN":null,"UNKNOWN_UNKNOWN2":null},{"Index":2,"HIT_STAND":{"Type":1,"Index":172,"DamageType":1,"Unused1":0,"NumberOfType1":1,"NumberOfType2":1,"Unused2":0,"Damage":10,"Stun":0,"Index9":0,"EXBuildAttacker":0,"EXBuildDefender":20,"Index12":0,"HitStunFramesAttacker":4,"HitStunFramesDefender":4,"FuzzyEffect":4,"RecoveryAnimationFramesDefender":18,"Index17":20,"Index18":0,"Index19":0,"KnockBack":0.3,"FallSpeed":0.6,"Index22":0,"Index23":0,"Index24":0,"Index25":0,"OffsetToStartOfType1":76,"OffsetToStartOfType2":88,"Type1s":[{"Unknown1":0,"SoundType":551,"Unknown3":0,"Unknown4":0}],"Type2s":[{"EffectType1":0,"EffectType2":0,"EffectType3":2,"Unknown4":0,"EffectPosition":-1,"Unknown6":0,"Unknown7":0,"Unknown8":0,"Unknown9":0,"Size":1.0,"Unknown11":0}]},"HIT_CROUCH":{"Type":1,"Index":172,"DamageType":1,"Unused1":0,"NumberOfType1":1,"NumberOfType2":1,"Unused2":0,"Damage":10,"Stun":0,"Index9":0,"EXBuildAttacker":0,"EXBuildDefender":20,"Index12":0,"HitStunFramesAttacker":4,"HitStunFramesDefender":4,"FuzzyEffect":4,"RecoveryAnimationFramesDefender":18,"Index17":20,"Index18":0,"Index19":0,"KnockBack":0.3,"FallSpeed":0.6,"Index22":0,"Index23":0,"Index24":0,"Index25":0,"OffsetToStartOfType1":76,"OffsetToStartOfType2":88,"Type1s":[{"Unknown1":0,"SoundType":551,"Unknown3":0,"Unknown4":0}],"Type2s":[{"EffectType1":0,"EffectType2":0,"EffectType3":2,"Unknown4":0,"EffectPosition":-1,"Unknown6":0,"Unknown7":0,"Unknown8":0,"Unknown9":0,"Size":1.0,"Unknown11":0}]},"HIT_AIR":{"Type":1,"Index":172,"DamageType":1,"Unused1":0,"NumberOfType1":1,"NumberOfType2":1,"Unused2":0,"Damage":10,"Stun":0,"Index9":0,"EXBuildAttacker":0,"EXBuildDefender":20,"Index12":0,"HitStunFramesAttacker":4,"HitStunFramesDefender":4,"FuzzyEffect":4,"RecoveryAnimationFramesDefender":18,"Index17":20,"Index18":0,"Index19":0,"KnockBack":0.3,"FallSpeed":0.6,"Index22":0,"Index23":0,"Index24":0,"Index25":0,"OffsetToStartOfType1":76,"OffsetToStartOfType2":88,"Type1s":[{"Unknown1":0,"SoundType":551,"Unknown3":0,"Unknown4":0}],"Type2s":[{"EffectType1":0,"EffectType2":0,"EffectType3":2,"Unknown4":0,"EffectPosition":-1,"Unknown6":0,"Unknown7":0,"Unknown8":0,"Unknown9":0,"Size":1.0,"Unknown11":0}]},"HIT_UNKNOWN":{"Type":1,"Index":172,"DamageType":1,"Unused1":0,"NumberOfType1":1,"NumberOfType2":1,"Unused2":0,"Damage":10,"Stun":0,"Index9":0,"EXBuildAttacker":0,"EXBuildDefender":20,"Index12":0,"HitStunFramesAttacker":4,"HitStunFramesDefender":4,"FuzzyEffect":4,"RecoveryAnimationFramesDefender":18,"Index17":20,"Index18":0,"Index19":0,"KnockBack":0.3,"FallSpeed":0.6,"Index22":0,"Index23":0,"Index24":0,"Index25":0,"OffsetToStartOfType1":76,"OffsetToStartOfType2":88,"Type1s":[{"Unknown1":0,"SoundType":551,"Unknown3":0,"Unknown4":0}],"Type2s":[{"EffectType1":0,"EffectType2":0,"EffectType3":2,"Unknown4":0,"EffectPosition":-1,"Unknown6":0,"Unknown7":0,"Unknown8":0,"Unknown9":0,"Size":1.0,"Unknown11":0}]},"HIT_UNKNOWN2":{"Type":0,"Index":-1,"DamageType":1,"Unused1":0,"NumberOfType1":1,"NumberOfType2":1,"Unused2":0,"Damage":0,"Stun":0,"Index9":0,"EXBuildAttacker":0,"EXBuildDefender":0,"Index12":0,"HitStunFramesAttacker":0,"HitStunFramesDefender":0,"FuzzyEffect":0,"RecoveryAnimationFramesDefender":0,"Index17":0,"Index18":257,"Index19":0,"KnockBack":0.0,"FallSpeed":0.0,"Index22":0,"Index23":0,"Index24":0,"Index25":0,"OffsetToStartOfType1":76,"OffsetToStartOfType2":88,"Type1s":[{"Unknown1":0,"SoundType":551,"Unknown3":0,"Unknown4":0}],"Type2s":[{"EffectType1":0,"EffectType2":0,"EffectType3":2,"Unknown4":0,"EffectPosition":-1,"Unknown6":0,"Unknown7":0,"Unknown8":0,"Unknown9":0,"Size":1.0,"Unknown11":0}]},"GUARD_STAND":{"Type":2,"Index":0,"DamageType":194,"Unused1":0,"NumberOfType1":1,"NumberOfType2":1,"Unused2":0,"Damage":3,"Stun":0,"Index9":0,"EXBuildAttacker":0,"EXBuildDefender":10,"Index12":0,"HitStunFramesAttacker":4,"HitStunFramesDefender":4,"FuzzyEffect":4,"RecoveryAnimationFramesDefender":6,"Index17":20,"Index18":1,"Index19":0,"KnockBack":0.0,"FallSpeed":0.0,"Index22":0,"Index23":0,"Index24":0,"Index25":0,"OffsetToStartOfType1":76,"OffsetToStartOfType2":88,"Type1s":[{"Unknown1":0,"SoundType":300,"Unknown3":0,"Unknown4":0}],"Type2s":[{"EffectType1":0,"EffectType2":0,"EffectType3":22,"Unknown4":0,"EffectPosition":-1,"Unknown6":0,"Unknown7":0,"Unknown8":0,"Unknown9":0,"Size":1.0,"Unknown11":0}]},"GUARD_CROUCH":{"Type":2,"Index":0,"DamageType":194,"Unused1":0,"NumberOfType1":1,"NumberOfType2":1,"Unused2":0,"Damage":3,"Stun":0,"Index9":0,"EXBuildAttacker":0,"EXBuildDefender":10,"Index12":0,"HitStunFramesAttacker":4,"HitStunFramesDefender":4,"FuzzyEffect":4,"RecoveryAnimationFramesDefender":6,"Index17":20,"Index18":1,"Index19":0,"KnockBack":0.0,"FallSpeed":0.0,"Index22":0,"Index23":0,"Index24":0,"Index25":0,"OffsetToStartOfType1":76,"OffsetToStartOfType2":88,"Type1s":[{"Unknown1":0,"SoundType":300,"Unknown3":0,"Unknown4":0}],"Type2s":[{"EffectType1":0,"EffectType2":0,"EffectType3":22,"Unknown4":0,"EffectPosition":-1,"Unknown6":0,"Unknown7":0,"Unknown8":0,"Unknown9":0,"Size":1.0,"Unknown11":0}]},"GUARD_AIR":{"Type":2,"Index":0,"DamageType":194,"Unused1":0,"NumberOfType1":1,"NumberOfType2":1,"Unused2":0,"Damage":3,"Stun":0,"Index9":0,"EXBuildAttacker":0,"EXBuildDefender":10,"Index12":0,"HitStunFramesAttacker":4,"HitStunFramesDefender":4,"FuzzyEffect":4,"RecoveryAnimationFramesDefender":6,"Index17":20,"Index18":1,"Index19":0,"KnockBack":0.0,"FallSpeed":0.0,"Index22":0,"Index23":0,"Index24":0,"Index25":0,"OffsetToStartOfType1":76,"OffsetToStartOfType2":88,"Type1s":[{"Unknown1":0,"SoundType":300,"Unknown3":0,"Unknown4":0}],"Type2s":[{"EffectType1":0,"EffectType2":0,"EffectType3":22,"Unknown4":0,"EffectPosition":-1,"Unknown6":0,"Unknown7":0,"Unknown8":0,"Unknown9":0,"Size":1.0,"Unknown11":0}]},"GUARD_UNKNOWN":{"Type":2,"Index":0,"DamageType":194,"Unused1":0,"NumberOfType1":1,"NumberOfType2":1,"Unused2":0,"Damage":3,"Stun":0,"Index9":0,"EXBuildAttacker":0,"EXBuildDefender":10,"Index12":0,"HitStunFramesAttacker":4,"HitStunFramesDefender":4,"FuzzyEffect":4,"RecoveryAnimationFramesDefender":6,"Index17":20,"Index18":1,"Index19":0,"KnockBack":0.0,"FallSpeed":0.0,"Index22":0,"Index23":0,"Index24":0,"Index25":0,"OffsetToStartOfType1":76,"OffsetToStartOfType2":88,"Type1s":[{"Unknown1":0,"SoundType":300,"Unknown3":0,"Unknown4":0}],"Type2s":[{"EffectType1":0,"EffectType2":0,"EffectType3":22,"Unknown4":0,"EffectPosition":-1,"Unknown6":0,"Unknown7":0,"Unknown8":0,"Unknown9":0,"Size":1.0,"Unknown11":0}]},"GUARD_UNKNOWN2":{"Type":0,"Index":-1,"DamageType":1,"Unused1":0,"NumberOfType1":1,"NumberOfType2":1,"Unused2":0,"Damage":0,"Stun":0,"Index9":0,"EXBuildAttacker":0,"EXBuildDefender":0,"Index12":0,"HitStunFramesAttacker":0,"HitStunFramesDefender":0,"FuzzyEffect":0,"RecoveryAnimationFramesDefender":0,"Index17":0,"Index18":257,"Index19":0,"KnockBack":0.0,"FallSpeed":0.0,"Index22":0,"Index23":0,"Index24":0,"Index25":0,"OffsetToStartOfType1":76,"OffsetToStartOfType2":88,"Type1s":[{"Unknown1":0,"SoundType":300,"Unknown3":0,"Unknown4":0}],"Type2s":[{"EffectType1":0,"EffectType2":0,"EffectType3":22,"Unknown4":0,"EffectPosition":-1,"Unknown6":0,"Unknown7":0,"Unknown8":0,"Unknown9":0,"Size":1.0,"Unknown11":0}]},"COUNTERHIT_STAND":{"Type":1,"Index":172,"DamageType":1,"Unused1":0,"NumberOfType1":1,"NumberOfType2":1,"Unused2":0,"Damage":12,"Stun":0,"Index9":0,"EXBuildAttacker":0,"EXBuildDefender":24,"Index12":0,"HitStunFramesAttacker":4,"HitStunFramesDefender":4,"FuzzyEffect":4,"RecoveryAnimationFramesDefender":20,"Index17":20,"Index18":0,"Index19":0,"KnockBack":0.4,"FallSpeed":0.5,"Index22":0,"Index23":0,"Index24":0,"Index25":0,"OffsetToStartOfType1":76,"OffsetToStartOfType2":88,"Type1s":[{"Unknown1":0,"SoundType":551,"Unknown3":0,"Unknown4":0}],"Type2s":[{"EffectType1":0,"EffectType2":0,"EffectType3":2,"Unknown4":0,"EffectPosition":-1,"Unknown6":0,"Unknown7":0,"Unknown8":0,"Unknown9":0,"Size":1.0,"Unknown11":0}]},"COUNTERHIT_CROUCH":{"Type":1,"Index":172,"DamageType":1,"Unused1":0,"NumberOfType1":1,"NumberOfType2":1,"Unused2":0,"Damage":12,"Stun":0,"Index9":0,"EXBuildAttacker":0,"EXBuildDefender":24,"Index12":0,"HitStunFramesAttacker":4,"HitStunFramesDefender":4,"FuzzyEffect":4,"RecoveryAnimationFramesDefender":20,"Index17":20,"Index18":0,"Index19":0,"KnockBack":0.4,"FallSpeed":0.5,"Index22":0,"Index23":0,"Index24":0,"Index25":0,"OffsetToStartOfType1":76,"OffsetToStartOfType2":88,"Type1s":[{"Unknown1":0,"SoundType":551,"Unknown3":0,"Unknown4":0}],"Type2s":[{"EffectType1":0,"EffectType2":0,"EffectType3":2,"Unknown4":0,"EffectPosition":-1,"Unknown6":0,"Unknown7":0,"Unknown8":0,"Unknown9":0,"Size":1.0,"Unknown11":0}]},"COUNTERHIT_AIR":{"Type":1,"Index":172,"DamageType":1,"Unused1":0,"NumberOfType1":1,"NumberOfType2":1,"Unused2":0,"Damage":12,"Stun":0,"Index9":0,"EXBuildAttacker":0,"EXBuildDefender":24,"Index12":0,"HitStunFramesAttacker":4,"HitStunFramesDefender":4,"FuzzyEffect":4,"RecoveryAnimationFramesDefender":20,"Index17":20,"Index18":0,"Index19":0,"KnockBack":0.4,"FallSpeed":0.5,"Index22":0,"Index23":0,"Index24":0,"Index25":0,"OffsetToStartOfType1":76,"OffsetToStartOfType2":88,"Type1s":[{"Unknown1":0,"SoundType":551,"Unknown3":0,"Unknown4":0}],"Type2s":[{"EffectType1":0,"EffectType2":0,"EffectType3":2,"Unknown4":0,"EffectPosition":-1,"Unknown6":0,"Unknown7":0,"Unknown8":0,"Unknown9":0,"Size":1.0,"Unknown11":0}]},"COUNTERHIT_UNKNOWN":{"Type":1,"Index":172,"DamageType":1,"Unused1":0,"NumberOfType1":1,"NumberOfType2":1,"Unused2":0,"Damage":12,"Stun":0,"Index9":0,"EXBuildAttacker":0,"EXBuildDefender":24,"Index12":0,"HitStunFramesAttacker":4,"HitStunFramesDefender":4,"FuzzyEffect":4,"RecoveryAnimationFramesDefender":20,"Index17":20,"Index18":0,"Index19":0,"KnockBack":0.4,"FallSpeed":0.5,"Index22":0,"Index23":0,"Index24":0,"Index25":0,"OffsetToStartOfType1":76,"OffsetToStartOfType2":88,"Type1s":[{"Unknown1":0,"SoundType":551,"Unknown3":0,"Unknown4":0}],"Type2s":[{"EffectType1":0,"EffectType2":0,"EffectType3":2,"Unknown4":0,"EffectPosition":-1,"Unknown6":0,"Unknown7":0,"Unknown8":0,"Unknown9":0,"Size":1.0,"Unknown11":0}]},"COUNTERHIT_UNKNOWN2":{"Type":0,"Index":-1,"DamageType":1,"Unused1":0,"NumberOfType1":1,"NumberOfType2":1,"Unused2":0,"Damage":0,"Stun":0,"Index9":0,"EXBuildAttacker":0,"EXBuildDefender":0,"Index12":0,"HitStunFramesAttacker":0,"HitStunFramesDefender":0,"FuzzyEffect":0,"RecoveryAnimationFramesDefender":0,"Index17":0,"Index18":257,"Index19":0,"KnockBack":0.0,"FallSpeed":0.0,"Index22":0,"Index23":0,"Index24":0,"Index25":0,"OffsetToStartOfType1":76,"OffsetToStartOfType2":88,"Type1s":[{"Unknown1":0,"SoundType":551,"Unknown3":0,"Unknown4":0}],"Type2s":[{"EffectType1":0,"EffectType2":0,"EffectType3":2,"Unknown4":0,"EffectPosition":-1,"Unknown6":0,"Unknown7":0,"Unknown8":0,"Unknown9":0,"Size":1.0,"Unknown11":0}]},"UNKNOWN_STAND":{"Type":0,"Index":-1,"DamageType":1,"Unused1":0,"NumberOfType1":0,"NumberOfType2":0,"Unused2":0,"Damage":10,"Stun":0,"Index9":0,"EXBuildAttacker":0,"EXBuildDefender":20,"Index12":0,"HitStunFramesAttacker":0,"HitStunFramesDefender":0,"FuzzyEffect":0,"RecoveryAnimationFramesDefender":0,"Index17":0,"Index18":257,"Index19":0,"KnockBack":0.0,"FallSpeed":0.0,"Index22":0,"Index23":0,"Index24":0,"Index25":0,"OffsetToStartOfType1":0,"OffsetToStartOfType2":0,"Type1s":[],"Type2s":[]},"UNKNOWN_CROUCH":{"Type":0,"Index":-1,"DamageType":1,"Unused1":0,"NumberOfType1":0,"NumberOfType2":0,"Unused2":0,"Damage":10,"Stun":0,"Index9":0,"EXBuildAttacker":0,"EXBuildDefender":20,"Index12":0,"HitStunFramesAttacker":0,"HitStunFramesDefender":0,"FuzzyEffect":0,"RecoveryAnimationFramesDefender":0,"Index17":0,"Index18":257,"Index19":0,"KnockBack":0.0,"FallSpeed":0.0,"Index22":0,"Index23":0,"Index24":0,"Index25":0,"OffsetToStartOfType1":0,"OffsetToStartOfType2":0,"Type1s":[],"Type2s":[]},"UNKNOWN_AIR":{"Type":0,"Index":-1,"DamageType":1,"Unused1":0,"NumberOfType1":0,"NumberOfType2":0,"Unused2":0,"Damage":10,"Stun":0,"Index9":0,"EXBuildAttacker":0,"EXBuildDefender":20,"Index12":0,"HitStunFramesAttacker":0,"HitStunFramesDefender":0,"FuzzyEffect":0,"RecoveryAnimationFramesDefender":0,"Index17":0,"Index18":257,"Index19":0,"KnockBack":0.0,"FallSpeed":0.0,"Index22":0,"Index23":0,"Index24":0,"Index25":0,"OffsetToStartOfType1":0,"OffsetToStartOfType2":0,"Type1s":[],"Type2s":[]},"UNKNOWN_UNKNOWN":{"Type":0,"Index":-1,"DamageType":1,"Unused1":0,"NumberOfType1":0,"NumberOfType2":0,"Unused2":0,"Damage":10,"Stun":0,"Index9":0,"EXBuildAttacker":0,"EXBuildDefender":20,"Index12":0,"HitStunFramesAttacker":0,"HitStunFramesDefender":0,"FuzzyEffect":0,"RecoveryAnimationFramesDefender":0,"Index17":0,"Index18":257,"Index19":0,"KnockBack":0.0,"FallSpeed":0.0,"Index22":0,"Index23":0,"Index24":0,"Index25":0,"OffsetToStartOfType1":0,"OffsetToStartOfType2":0,"Type1s":[],"Type2s":[]},"UNKNOWN_UNKNOWN2":{"Type":0,"Index":-1,"DamageType":1,"Unused1":0,"NumberOfType1":0,"NumberOfType2":0,"Unused2":0,"Damage":0,"Stun":0,"Index9":0,"EXBuildAttacker":0,"EXBuildDefender":0,"Index12":0,"HitStunFramesAttacker":0,"HitStunFramesDefender":0,"FuzzyEffect":0,"RecoveryAnimationFramesDefender":0,"Index17":0,"Index18":257,"Index19":0,"KnockBack":0.0,"FallSpeed":0.0,"Index22":0,"Index23":0,"Index24":0,"Index25":0,"OffsetToStartOfType1":0,"OffsetToStartOfType2":0,"Type1s":[],"Type2s":[]}},{"Index":3,"HIT_STAND":null,"HIT_CROUCH":null,"HIT_AIR":null,"HIT_UNKNOWN":null,"HIT_UNKNOWN2":null,"GUARD_STAND":null,"GUARD_CROUCH":null,"GUARD_AIR":null,"GUARD_UNKNOWN":null,"GUARD_UNKNOWN2":null,"COUNTERHIT_STAND":null,"COUNTERHIT_CROUCH":null,"COUNTERHIT_AIR":null,"COUNTERHIT_UNKNOWN":null,"COUNTERHIT_UNKNOWN2":null,"UNKNOWN_STAND":null,"UNKNOWN_CROUCH":null,"UNKNOWN_AIR":null,"UNKNOWN_UNKNOWN":null,"UNKNOWN_UNKNOWN2":null},{"Index":4,"HIT_STAND":{"Type":1,"Index":172,"DamageType":1,"Unused1":0,"NumberOfType1":3,"NumberOfType2":2,"Unused2":0,"Damage":10,"Stun":0,"Index9":0,"EXBuildAttacker":0,"EXBuildDefender":20,"Index12":0,"HitStunFramesAttacker":4,"HitStunFramesDefender":4,"FuzzyEffect":4,"RecoveryAnimationFramesDefender":19,"Index17":20,"Index18":0,"Index19":0,"KnockBack":0.4,"FallSpeed":0.5,"Index22":0,"Index23":0,"Index24":0,"Index25":0,"OffsetToStartOfType1":76,"OffsetToStartOfType2":112,"Type1s":[{"Unknown1":0,"SoundType":59,"Unknown3":0,"Unknown4":0},{"Unknown1":0,"SoundType":550,"Unknown3":0,"Unknown4":0},{"Unknown1":0,"SoundType":27,"Unknown3":8,"Unknown4":0}],"Type2s":[{"EffectType1":0,"EffectType2":2,"EffectType3":65,"Unknown4":0,"EffectPosition":-1,"Unknown6":0,"Unknown7":0,"Unknown8":0,"Unknown9":0,"Size":1.0,"Unknown11":0},{"EffectType1":0,"EffectType2":0,"EffectType3":3,"Unknown4":0,"EffectPosition":-1,"Unknown6":0,"Unknown7":0,"Unknown8":0,"Unknown9":0,"Size":1.0,"Unknown11":0}]},"HIT_CROUCH":{"Type":1,"Index":172,"DamageType":1,"Unused1":0,"NumberOfType1":3,"NumberOfType2":2,"Unused2":0,"Damage":10,"Stun":0,"Index9":0,"EXBuildAttacker":0,"EXBuildDefender":20,"Index12":0,"HitStunFramesAttacker":4,"HitStunFramesDefender":4,"FuzzyEffect":4,"RecoveryAnimationFramesDefender":19,"Index17":20,"Index18":0,"Index19":0,"KnockBack":0.4,"FallSpeed":0.5,"Index22":0,"Index23":0,"Index24":0,"Index25":0,"OffsetToStartOfType1":76,"OffsetToStartOfType2":112,"Type1s":[{"Unknown1":0,"SoundType":59,"Unknown3":0,"Unknown4":0},{"Unknown1":0,"SoundType":550,"Unknown3":0,"Unknown4":0},{"Unknown1":0,"SoundType":27,"Unknown3":8,"Unknown4":0}],"Type2s":[{"EffectType1":0,"EffectType2":2,"EffectType3":65,"Unknown4":0,"EffectPosition":-1,"Unknown6":0,"Unknown7":0,"Unknown8":0,"Unknown9":0,"Size":1.0,"Unknown11":0},{"EffectType1":0,"EffectType2":0,"EffectType3":3,"Unknown4":0,"EffectPosition":-1,"Unknown6":0,"Unknown7":0,"Unknown8":0,"Unknown9":0,"Size":1.0,"Unknown11":0}]},"HIT_AIR":{"Type":1,"Index":172,"DamageType":1,"Unused1":0,"NumberOfType1":3,"NumberOfType2":2,"Unused2":0,"Damage":10,"Stun":0,"Index9":0,"EXBuildAttacker":0,"EXBuildDefender":20,"Index12":0,"HitStunFramesAttacker":4,"HitStunFramesDefender":4,"FuzzyEffect":4,"RecoveryAnimationFramesDefender":19,"Index17":20,"Index18":0,"Index19":0,"KnockBack":0.4,"FallSpeed":0.5,"Index22":0,"Index23":0,"Index24":0,"Index25":0,"OffsetToStartOfType1":76,"OffsetToStartOfType2":112,"Type1s":[{"Unknown1":0,"SoundType":59,"Unknown3":0,"Unknown4":0},{"Unknown1":0,"SoundType":550,"Unknown3":0,"Unknown4":0},{"Unknown1":0,"SoundType":27,"Unknown3":8,"Unknown4":0}],"Type2s":[{"EffectType1":0,"EffectType2":2,"EffectType3":65,"Unknown4":0,"EffectPosition":-1,"Unknown6":0,"Unknown7":0,"Unknown8":0,"Unknown9":0,"Size":1.0,"Unknown11":0},{"EffectType1":0,"EffectType2":0,"EffectType3":3,"Unknown4":0,"EffectPosition":-1,"Unknown6":0,"Unknown7":0,"Unknown8":0,"Unknown9":0,"Size":1.0,"Unknown11":0}]},"HIT_UNKNOWN":{"Type":1,"Index":172,"DamageType":1,"Unused1":0,"NumberOfType1":3,"NumberOfType2":2,"Unused2":0,"Damage":10,"Stun":0,"Index9":0,"EXBuildAttacker":0,"EXBuildDefender":20,"Index12":0,"HitStunFramesAttacker":4,"HitStunFramesDefender":4,"FuzzyEffect":4,"RecoveryAnimationFramesDefender":19,"Index17":20,"Index18":0,"Index19":0,"KnockBack":0.4,"FallSpeed":0.5,"Index22":0,"Index23":0,"Index24":0,"Index25":0,"OffsetToStartOfType1":76,"OffsetToStartOfType2":112,"Type1s":[{"Unknown1":0,"SoundType":59,"Unknown3":0,"Unknown4":0},{"Unknown1":0,"SoundType":550,"Unknown3":0,"Unknown4":0},{"Unknown1":0,"SoundType":27,"Unknown3":8,"Unknown4":0}],"Type2s":[{"EffectType1":0,"EffectType2":2,"EffectType3":65,"Unknown4":0,"EffectPosition":-1,"Unknown6":0,"Unknown7":0,"Unknown8":0,"Unknown9":0,"Size":1.0,"Unknown11":0},{"EffectType1":0,"EffectType2":0,"EffectType3":3,"Unknown4":0,"EffectPosition":-1,"Unknown6":0,"Unknown7":0,"Unknown8":0,"Unknown9":0,"Size":1.0,"Unknown11":0}]},"HIT_UNKNOWN2":{"Type":0,"Index":-1,"DamageType":1,"Unused1":0,"NumberOfType1":3,"NumberOfType2":2,"Unused2":0,"Damage":0,"Stun":0,"Index9":0,"EXBuildAttacker":0,"EXBuildDefender":0,"Index12":0,"HitStunFramesAttacker":0,"HitStunFramesDefender":0,"FuzzyEffect":0,"RecoveryAnimationFramesDefender":0,"Index17":0,"Index18":257,"Index19":0,"KnockBack":0.0,"FallSpeed":0.0,"Index22":0,"Index23":0,"Index24":0,"Index25":0,"OffsetToStartOfType1":76,"OffsetToStartOfType2":112,"Type1s":[{"Unknown1":0,"SoundType":59,"Unknown3":0,"Unknown4":0},{"Unknown1":0,"SoundType":550,"Unknown3":0,"Unknown4":0},{"Unknown1":0,"SoundType":27,"Unknown3":8,"Unknown4":0}],"Type2s":[{"EffectType1":0,"EffectType2":2,"EffectType3":65,"Unknown4":0,"EffectPosition":-1,"Unknown6":0,"Unknown7":0,"Unknown8":0,"Unknown9":0,"Size":1.0,"Unknown11":0},{"EffectType1":0,"EffectType2":0,"EffectType3":3,"Unknown4":0,"EffectPosition":-1,"Unknown6":0,"Unknown7":0,"Unknown8":0,"Unknown9":0,"Size":1.0,"Unknown11":0}]},"GUARD_STAND":{"Type":2,"Index":0,"DamageType":194,"Unused1":0,"NumberOfType1":2,"NumberOfType2":2,"Unused2":0,"Damage":3,"Stun":0,"Index9":0,"EXBuildAttacker":0,"EXBuildDefender":10,"Index12":0,"HitStunFramesAttacker":4,"HitStunFramesDefender":4,"FuzzyEffect":4,"RecoveryAnimationFramesDefender":16,"Index17":20,"Index18":0,"Index19":0,"KnockBack":0.0,"FallSpeed":0.0,"Index22":0,"Index23":0,"Index24":0,"Index25":0,"OffsetToStartOfType1":76,"OffsetToStartOfType2":100,"Type1s":[{"Unknown1":0,"SoundType":300,"Unknown3":0,"Unknown4":0},{"Unknown1":0,"SoundType":27,"Unknown3":8,"Unknown4":0}],"Type2s":[{"EffectType1":0,"EffectType2":0,"EffectType3":21,"Unknown4":0,"EffectPosition":-1,"Unknown6":0,"Unknown7":0,"Unknown8":0,"Unknown9":0,"Size":1.0,"Unknown11":0},{"EffectType1":0,"EffectType2":2,"EffectType3":65,"Unknown4":0,"EffectPosition":-1,"Unknown6":0,"Unknown7":0,"Unknown8":0,"Unknown9":0,"Size":1.0,"Unknown11":0}]},"GUARD_CROUCH":{"Type":2,"Index":0,"DamageType":194,"Unused1":0,"NumberOfType1":2,"NumberOfType2":2,"Unused2":0,"Damage":3,"Stun":0,"Index9":0,"EXBuildAttacker":0,"EXBuildDefender":10,"Index12":0,"HitStunFramesAttacker":4,"HitStunFramesDefender":4,"FuzzyEffect":4,"RecoveryAnimationFramesDefender":16,"Index17":20,"Index18":0,"Index19":0,"KnockBack":0.0,"FallSpeed":0.0,"Index22":0,"Index23":0,"Index24":0,"Index25":0,"OffsetToStartOfType1":76,"OffsetToStartOfType2":100,"Type1s":[{"Unknown1":0,"SoundType":300,"Unknown3":0,"Unknown4":0},{"Unknown1":0,"SoundType":27,"Unknown3":8,"Unknown4":0}],"Type2s":[{"EffectType1":0,"EffectType2":0,"EffectType3":21,"Unknown4":0,"EffectPosition":-1,"Unknown6":0,"Unknown7":0,"Unknown8":0,"Unknown9":0,"Size":1.0,"Unknown11":0},{"EffectType1":0,"EffectType2":2,"EffectType3":65,"Unknown4":0,"EffectPosition":-1,"Unknown6":0,"Unknown7":0,"Unknown8":0,"Unknown9":0,"Size":1.0,"Unknown11":0}]},"GUARD_AIR":{"Type":2,"Index":0,"DamageType":194,"Unused1":0,"NumberOfType1":2,"NumberOfType2":2,"Unused2":0,"Damage":3,"Stun":0,"Index9":0,"EXBuildAttacker":0,"EXBuildDefender":10,"Index12":0,"HitStunFramesAttacker":4,"HitStunFramesDefender":4,"FuzzyEffect":4,"RecoveryAnimationFramesDefender":16,"Index17":20,"Index18":0,"Index19":0,"KnockBack":0.0,"FallSpeed":0.0,"Index22":0,"Index23":0,"Index24":0,"Index25":0,"OffsetToStartOfType1":76,"OffsetToStartOfType2":100,"Type1s":[{"Unknown1":0,"SoundType":300,"Unknown3":0,"Unknown4":0},{"Unknown1":0,"SoundType":27,"Unknown3":8,"Unknown4":0}],"Type2s":[{"EffectType1":0,"EffectType2":0,"EffectType3":21,"Unknown4":0,"EffectPosition":-1,"Unknown6":0,"Unknown7":0,"Unknown8":0,"Unknown9":0,"Size":1.0,"Unknown11":0},{"EffectType1":0,"EffectType2":2,"EffectType3":65,"Unknown4":0,"EffectPosition":-1,"Unknown6":0,"Unknown7":0,"Unknown8":0,"Unknown9":0,"Size":1.0,"Unknown11":0}]},"GUARD_UNKNOWN":{"Type":2,"Index":0,"DamageType":194,"Unused1":0,"NumberOfType1":2,"NumberOfType2":2,"Unused2":0,"Damage":3,"Stun":0,"Index9":0,"EXBuildAttacker":0,"EXBuildDefender":10,"Index12":0,"HitStunFramesAttacker":4,"HitStunFramesDefender":4,"FuzzyEffect":4,"RecoveryAnimationFramesDefender":16,"Index17":20,"Index18":0,"Index19":0,"KnockBack":0.0,"FallSpeed":0.0,"Index22":0,"Index23":0,"Index24":0,"Index25":0,"OffsetToStartOfType1":76,"OffsetToStartOfType2":100,"Type1s":[{"Unknown1":0,"SoundType":300,"Unknown3":0,"Unknown4":0},{"Unknown1":0,"SoundType":27,"Unknown3":8,"Unknown4":0}],"Type2s":[{"EffectType1":0,"EffectType2":0,"EffectType3":21,"Unknown4":0,"EffectPosition":-1,"Unknown6":0,"Unknown7":0,"Unknown8":0,"Unknown9":0,"Size":1.0,"Unknown11":0},{"EffectType1":0,"EffectType2":2,"EffectType3":65,"Unknown4":0,"EffectPosition":-1,"Unknown6":0,"Unknown7":0,"Unknown8":0,"Unknown9":0,"Size":1.0,"Unknown11":0}]},"GUARD_UNKNOWN2":{"Type":0,"Index":-1,"DamageType":1,"Unused1":0,"NumberOfType1":2,"NumberOfType2":2,"Unused2":0,"Damage":0,"Stun":0,"Index9":0,"EXBuildAttacker":0,"EXBuildDefender":0,"Index12":0,"HitStunFramesAttacker":0,"HitStunFramesDefender":0,"FuzzyEffect":0,"RecoveryAnimationFramesDefender":0,"Index17":0,"Index18":257,"Index19":0,"KnockBack":0.0,"FallSpeed":0.0,"Index22":0,"Index23":0,"Index24":0,"Index25":0,"OffsetToStartOfType1":76,"OffsetToStartOfType2":100,"Type1s":[{"Unknown1":0,"SoundType":300,"Unknown3":0,"Unknown4":0},{"Unknown1":0,"SoundType":27,"Unknown3":8,"Unknown4":0}],"Type2s":[{"EffectType1":0,"EffectType2":0,"EffectType3":21,"Unknown4":0,"EffectPosition":-1,"Unknown6":0,"Unknown7":0,"Unknown8":0,"Unknown9":0,"Size":1.0,"Unknown11":0},{"EffectType1":0,"EffectType2":2,"EffectType3":65,"Unknown4":0,"EffectPosition":-1,"Unknown6":0,"Unknown7":0,"Unknown8":0,"Unknown9":0,"Size":1.0,"Unknown11":0}]},"COUNTERHIT_STAND":{"Type":1,"Index":172,"DamageType":1,"Unused1":0,"NumberOfType1":3,"NumberOfType2":2,"Unused2":0,"Damage":12,"Stun":0,"Index9":0,"EXBuildAttacker":0,"EXBuildDefender":24,"Index12":0,"HitStunFramesAttacker":4,"HitStunFramesDefender":4,"FuzzyEffect":4,"RecoveryAnimationFramesDefender":21,"Index17":20,"Index18":0,"Index19":0,"KnockBack":0.4,"FallSpeed":0.5,"Index22":0,"Index23":0,"Index24":0,"Index25":0,"OffsetToStartOfType1":76,"OffsetToStartOfType2":112,"Type1s":[{"Unknown1":0,"SoundType":59,"Unknown3":0,"Unknown4":0},{"Unknown1":0,"SoundType":550,"Unknown3":0,"Unknown4":0},{"Unknown1":0,"SoundType":27,"Unknown3":8,"Unknown4":0}],"Type2s":[{"EffectType1":0,"EffectType2":2,"EffectType3":65,"Unknown4":0,"EffectPosition":-1,"Unknown6":0,"Unknown7":0,"Unknown8":0,"Unknown9":0,"Size":1.0,"Unknown11":0},{"EffectType1":0,"EffectType2":0,"EffectType3":3,"Unknown4":0,"EffectPosition":-1,"Unknown6":0,"Unknown7":0,"Unknown8":0,"Unknown9":0,"Size":1.0,"Unknown11":0}]},"COUNTERHIT_CROUCH":{"Type":1,"Index":172,"DamageType":1,"Unused1":0,"NumberOfType1":3,"NumberOfType2":2,"Unused2":0,"Damage":12,"Stun":0,"Index9":0,"EXBuildAttacker":0,"EXBuildDefender":24,"Index12":0,"HitStunFramesAttacker":4,"HitStunFramesDefender":4,"FuzzyEffect":4,"RecoveryAnimationFramesDefender":21,"Index17":20,"Index18":0,"Index19":0,"KnockBack":0.4,"FallSpeed":0.5,"Index22":0,"Index23":0,"Index24":0,"Index25":0,"OffsetToStartOfType1":76,"OffsetToStartOfType2":112,"Type1s":[{"Unknown1":0,"SoundType":59,"Unknown3":0,"Unknown4":0},{"Unknown1":0,"SoundType":550,"Unknown3":0,"Unknown4":0},{"Unknown1":0,"SoundType":27,"Unknown3":8,"Unknown4":0}],"Type2s":[{"EffectType1":0,"EffectType2":2,"EffectType3":65,"Unknown4":0,"EffectPosition":-1,"Unknown6":0,"Unknown7":0,"Unknown8":0,"Unknown9":0,"Size":1.0,"Unknown11":0},{"EffectType1":0,"EffectType2":0,"EffectType3":3,"Unknown4":0,"EffectPosition":-1,"Unknown6":0,"Unknown7":0,"Unknown8":0,"Unknown9":0,"Size":1.0,"Unknown11":0}]},"COUNTERHIT_AIR":{"Type":1,"Index":172,"DamageType":1,"Unused1":0,"NumberOfType1":3,"NumberOfType2":2,"Unused2":0,"Damage":12,"Stun":0,"Index9":0,"EXBuildAttacker":0,"EXBuildDefender":24,"Index12":0,"HitStunFramesAttacker":4,"HitStunFramesDefender":4,"FuzzyEffect":4,"RecoveryAnimationFramesDefender":21,"Index17":20,"Index18":0,"Index19":0,"KnockBack":0.4,"FallSpeed":0.5,"Index22":0,"Index23":0,"Index24":0,"Index25":0,"OffsetToStartOfType1":76,"OffsetToStartOfType2":112,"Type1s":[{"Unknown1":0,"SoundType":59,"Unknown3":0,"Unknown4":0},{"Unknown1":0,"SoundType":550,"Unknown3":0,"Unknown4":0},{"Unknown1":0,"SoundType":27,"Unknown3":8,"Unknown4":0}],"Type2s":[{"EffectType1":0,"EffectType2":2,"EffectType3":65,"Unknown4":0,"EffectPosition":-1,"Unknown6":0,"Unknown7":0,"Unknown8":0,"Unknown9":0,"Size":1.0,"Unknown11":0},{"EffectType1":0,"EffectType2":0,"EffectType3":3,"Unknown4":0,"EffectPosition":-1,"Unknown6":0,"Unknown7":0,"Unknown8":0,"Unknown9":0,"Size":1.0,"Unknown11":0}]},"COUNTERHIT_UNKNOWN":{"Type":1,"Index":172,"DamageType":1,"Unused1":0,"NumberOfType1":3,"NumberOfType2":2,"Unused2":0,"Damage":12,"Stun":0,"Index9":0,"EXBuildAttacker":0,"EXBuildDefender":24,"Index12":0,"HitStunFramesAttacker":4,"HitStunFramesDefender":4,"FuzzyEffect":4,"RecoveryAnimationFramesDefender":21,"Index17":20,"Index18":0,"Index19":0,"KnockBack":0.4,"FallSpeed":0.5,"Index22":0,"Index23":0,"Index24":0,"Index25":0,"OffsetToStartOfType1":76,"OffsetToStartOfType2":112,"Type1s":[{"Unknown1":0,"SoundType":59,"Unknown3":0,"Unknown4":0},{"Unknown1":0,"SoundType":550,"Unknown3":0,"Unknown4":0},{"Unknown1":0,"SoundType":27,"Unknown3":8,"Unknown4":0}],"Type2s":[{"EffectType1":0,"EffectType2":2,"EffectType3":65,"Unknown4":0,"EffectPosition":-1,"Unknown6":0,"Unknown7":0,"Unknown8":0,"Unknown9":0,"Size":1.0,"Unknown11":0},{"EffectType1":0,"EffectType2":0,"EffectType3":3,"Unknown4":0,"EffectPosition":-1,"Unknown6":0,"Unknown7":0,"Unknown8":0,"Unknown9":0,"Size":1.0,"Unknown11":0}]},"COUNTERHIT_UNKNOWN2":{"Type":0,"Index":-1,"DamageType":1,"Unused1":0,"NumberOfType1":3,"NumberOfType2":2,"Unused2":0,"Damage":0,"Stun":0,"Index9":0,"EXBuildAttacker":0,"EXBuildDefender":0,"Index12":0,"HitStunFramesAttacker":0,"HitStunFramesDefender":0,"FuzzyEffect":0,"RecoveryAnimationFramesDefender":0,"Index17":0,"Index18":257,"Index19":0,"KnockBack":0.0,"FallSpeed":0.0,"Index22":0,"Index23":0,"Index24":0,"Index25":0,"OffsetToStartOfType1":76,"OffsetToStartOfType2":112,"Type1s":[{"Unknown1":0,"SoundType":59,"Unknown3":0,"Unknown4":0},{"Unknown1":0,"SoundType":550,"Unknown3":0,"Unknown4":0},{"Unknown1":0,"SoundType":27,"Unknown3":8,"Unknown4":0}],"Type2s":[{"EffectType1":0,"EffectType2":2,"EffectType3":65,"Unknown4":0,"EffectPosition":-1,"Unknown6":0,"Unknown7":0,"Unknown8":0,"Unknown9":0,"Size":1.0,"Unknown11":0},{"EffectType1":0,"EffectType2":0,"EffectType3":3,"Unknown4":0,"EffectPosition":-1,"Unknown6":0,"Unknown7":0,"Unknown8":0,"Unknown9":0,"Size":1.0,"Unknown11":0}]},"UNKNOWN_STAND":{"Type":0,"Index":-1,"DamageType":1,"Unused1":0,"NumberOfType1":0,"NumberOfType2":0,"Unused2":0,"Damage":10,"Stun":0,"Index9":0,"EXBuildAttacker":0,"EXBuildDefender":20,"Index12":0,"HitStunFramesAttacker":0,"HitStunFramesDefender":0,"FuzzyEffect":0,"RecoveryAnimationFramesDefender":0,"Index17":0,"Index18":257,"Index19":0,"KnockBack":0.0,"FallSpeed":0.0,"Index22":0,"Index23":0,"Index24":0,"Index25":0,"OffsetToStartOfType1":0,"OffsetToStartOfType2":0,"Type1s":[],"Type2s":[]},"UNKNOWN_CROUCH":{"Type":0,"Index":-1,"DamageType":1,"Unused1":0,"NumberOfType1":0,"NumberOfType2":0,"Unused2":0,"Damage":10,"Stun":0,"Index9":0,"EXBuildAttacker":0,"EXBuildDefender":20,"Index12":0,"HitStunFramesAttacker":0,"HitStunFramesDefender":0,"FuzzyEffect":0,"RecoveryAnimationFramesDefender":0,"Index17":0,"Index18":257,"Index19":0,"KnockBack":0.0,"FallSpeed":0.0,"Index22":0,"Index23":0,"Index24":0,"Index25":0,"OffsetToStartOfType1":0,"OffsetToStartOfType2":0,"Type1s":[],"Type2s":[]},"UNKNOWN_AIR":{"Type":0,"Index":-1,"DamageType":1,"Unused1":0,"NumberOfType1":0,"NumberOfType2":0,"Unused2":0,"Damage":10,"Stun":0,"Index9":0,"EXBuildAttacker":0,"EXBuildDefender":20,"Index12":0,"HitStunFramesAttacker":0,"HitStunFramesDefender":0,"FuzzyEffect":0,"RecoveryAnimationFramesDefender":0,"Index17":0,"Index18":257,"Index19":0,"KnockBack":0.0,"FallSpeed":0.0,"Index22":0,"Index23":0,"Index24":0,"Index25":0,"OffsetToStartOfType1":0,"OffsetToStartOfType2":0,"Type1s":[],"Type2s":[]},"UNKNOWN_UNKNOWN":{"Type":0,"Index":-1,"DamageType":1,"Unused1":0,"NumberOfType1":0,"NumberOfType2":0,"Unused2":0,"Damage":10,"Stun":0,"Index9":0,"EXBuildAttacker":0,"EXBuildDefender":20,"Index12":0,"HitStunFramesAttacker":0,"HitStunFramesDefender":0,"FuzzyEffect":0,"RecoveryAnimationFramesDefender":0,"Index17":0,"Index18":257,"Index19":0,"KnockBack":0.0,"FallSpeed":0.0,"Index22":0,"Index23":0,"Index24":0,"Index25":0,"OffsetToStartOfType1":0,"OffsetToStartOfType2":0,"Type1s":[],"Type2s":[]},"UNKNOWN_UNKNOWN2":{"Type":0,"Index":-1,"DamageType":1,"Unused1":0,"NumberOfType1":0,"NumberOfType2":0,"Unused2":0,"Damage":0,"Stun":0,"Index9":0,"EXBuildAttacker":0,"EXBuildDefender":0,"Index12":0,"HitStunFramesAttacker":0,"HitStunFramesDefender":0,"FuzzyEffect":0,"RecoveryAnimationFramesDefender":0,"Index17":0,"Index18":257,"Index19":0,"KnockBack":0.0,"FallSpeed":0.0,"Index22":0,"Index23":0,"Index24":0,"Index25":0,"OffsetToStartOfType1":0,"OffsetToStartOfType2":0,"Type1s":[],"Type2s":[]}}],"RawUassetHeaderDontTouch":"wYMqnvv///8AAAAAAAAAAAAAAAAAAAAA7AEAAAUAAABOb25lAAAAAIALAAAAowAAAAEAAACgAQAAAgAAAGgBAADkAQAAAAAAAOgBAAAAAAAAdseX7uRyzEiIOmG8KqD0yQEAAAABAAAACwAAAAAAAAAAAAAAAAAAAAAAAAAAAAAAAABiRaJyAAAAAAAAAADoAQAA8CMAAAAAAAAAAAAAAAAAAC8AAAAvR2FtZS9DaGFyYS9CUkQvQmF0dGxlUmVzb3VyY2UvMDAwL0JBQ19CUkRfZWZmABQAAAAvU2NyaXB0L0NvcmVVT2JqZWN0ABEAAAAvU2NyaXB0L0tpd2lHYW1lAA4AAABBcnJheVByb3BlcnR5AAwAAABCQUNfQlJEX2VmZgANAAAAQnl0ZVByb3BlcnR5AAYAAABDbGFzcwAFAAAARGF0YQAGAAAAS1dCQUMABQAAAE5vbmUACAAAAFBhY2thZ2UAAQAAAAAAAAAGAAAAAAAAAP7///8IAAAAAAAAAAEAAAAAAAAACgAAAAAAAAAAAAAAAgAAAAAAAAD/////AAAAAAAAAAAEAAAAAAAAAAMAAAAEIgAA7AEAAAAAAAAAAAAAAAAAAAAAAAAAAAAAAAAAAAAAAAAAAAAAAQAAAAAAAAAAAAAA"}